topo_metrics/__init__.py
topo_metrics/_julia_wrappers.py
topo_metrics/clusters.py
topo_metrics/paths.py
topo_metrics/rings.py
topo_metrics/symbols.py
topo_metrics/topology.py
topo_metrics/utils.py
topo_metrics/RingStatistics/Manifest.toml
topo_metrics/RingStatistics/Project.toml
topo_metrics/RingStatistics/deps/build.jl
topo_metrics/RingStatistics/deps/build.log
topo_metrics/RingStatistics/src/RingStatistics.jl
topo_metrics/RingStatistics/src/precompile.jl
topo_metrics/RingStatistics/test/runtests.jl
topo_metrics/io/__init__.py
topo_metrics/io/cgd.py
topo_metrics-0.1.2.dist-info/licenses/LICENSE
topo_metrics-0.1.2.dist-info/METADATA
topo_metrics-0.1.2.dist-info/WHEEL
topo_metrics-0.1.2.dist-info/top_level.txt
topo_metrics-0.1.2.dist-info/RECORD
