Metadata-Version: 2.4
Name: topo-metrics
Version: 0.1.2
Summary: Topological analysis tools for network materials.
Author-email: Thomas Nicholas <tcnicholas@me.com>
License: MIT License
Project-URL: Homepage, https://github.com/tcnicholas/topo-metrics
Classifier: License :: OSI Approved :: MIT License
Classifier: Programming Language :: Python
Classifier: Programming Language :: Python :: 3.10
Classifier: Programming Language :: Python :: 3.11
Classifier: Programming Language :: Python :: 3.12
Requires-Python: >=3.10
License-File: LICENSE
Requires-Dist: setuptools
Requires-Dist: wheel
Requires-Dist: pymatgen>=2025.3.10
Requires-Dist: pytest>=8.3.5
Requires-Dist: juliacall>=0.9.24
Provides-Extra: tests
Requires-Dist: pytest; extra == "tests"
Requires-Dist: pytest-cov; extra == "tests"
Provides-Extra: dev
Requires-Dist: bumpver; extra == "dev"
Requires-Dist: ruff; extra == "dev"
Provides-Extra: publish
Requires-Dist: build; extra == "publish"
Requires-Dist: twine; extra == "publish"
Dynamic: license-file
